sensorpush_ha/__init__.py
sensorpush_ha/api.py
sensorpush_ha/helper.py
sensorpush_ha/py.typed
sensorpush_ha-1.2.0.dist-info/LICENSE
sensorpush_ha-1.2.0.dist-info/METADATA
sensorpush_ha-1.2.0.dist-info/WHEEL
sensorpush_ha-1.2.0.dist-info/top_level.txt
sensorpush_ha-1.2.0.dist-info/RECORD
