Metadata-Version: 2.1
Name: sensorpush-ha
Version: 1.2.0
Summary: SensorPush Cloud Home Assistant Library
Home-page: https://github.com/sstallion/sensorpush-ha
Author: Steven Stallion
Author-email: sstallion@gmail.com
License: BSD-2-Clause
Keywords: homeassistant sensorpush
Classifier: Development Status :: 5 - Production/Stable
Classifier: Environment :: Web Environment
Classifier: Intended Audience :: Developers
Classifier: License :: OSI Approved :: BSD License
Classifier: Operating System :: OS Independent
Classifier: Programming Language :: Python
Classifier: Programming Language :: Python :: 3
Classifier: Programming Language :: Python :: 3.12
Classifier: Programming Language :: Python :: 3.13
Classifier: Topic :: Internet :: WWW/HTTP
Classifier: Topic :: Software Development :: Libraries
Classifier: Topic :: Software Development :: Libraries :: Python Modules
License-File: LICENSE
Requires-Dist: sensorpush-api>=2.1.0
Provides-Extra: release
Requires-Dist: build>=0.3.0; extra == "release"
